LICENSE.txt
MANIFEST.in
README.md
main.py
setup.py
pysvap.egg-info/SOURCES.txt
pysvap.egg-info/dependency_links.txt
pysvap.egg-info/requires.txt
pysvap.egg-info/top_level.txt
src/functions/blur.py
src/functions/colorShift.py
src/functions/darken.py
src/functions/grayScale.py
src/functions/hue.py
src/functions/lighten.py
src/functions/negative.py
src/functions/overlay.py
src/functions/pixelate.py
src/functions/posterize.py
src/functions/saturate.py
src/functions/sepia.py
src/functions/temp.py
src/pysvap.egg-info/PKG-INFO
src/pysvap.egg-info/SOURCES.txt
src/pysvap.egg-info/dependency_links.txt
src/pysvap.egg-info/requires.txt
src/pysvap.egg-info/top_level.txt
src/pythonfiles/__init__.py
venv/lib/python3.8/site-packages/PIL/BdfFontFile.py
venv/lib/python3.8/site-packages/PIL/BlpImagePlugin.py
venv/lib/python3.8/site-packages/PIL/BmpImagePlugin.py
venv/lib/python3.8/site-packages/PIL/BufrStubImagePlugin.py
venv/lib/python3.8/site-packages/PIL/ContainerIO.py
venv/lib/python3.8/site-packages/PIL/CurImagePlugin.py
venv/lib/python3.8/site-packages/PIL/DcxImagePlugin.py
venv/lib/python3.8/site-packages/PIL/DdsImagePlugin.py
venv/lib/python3.8/site-packages/PIL/EpsImagePlugin.py
venv/lib/python3.8/site-packages/PIL/ExifTags.py
venv/lib/python3.8/site-packages/PIL/FitsStubImagePlugin.py
venv/lib/python3.8/site-packages/PIL/FliImagePlugin.py
venv/lib/python3.8/site-packages/PIL/FontFile.py
venv/lib/python3.8/site-packages/PIL/FpxImagePlugin.py
venv/lib/python3.8/site-packages/PIL/FtexImagePlugin.py
venv/lib/python3.8/site-packages/PIL/GbrImagePlugin.py
venv/lib/python3.8/site-packages/PIL/GdImageFile.py
venv/lib/python3.8/site-packages/PIL/GifImagePlugin.py
venv/lib/python3.8/site-packages/PIL/GimpGradientFile.py
venv/lib/python3.8/site-packages/PIL/GimpPaletteFile.py
venv/lib/python3.8/site-packages/PIL/GribStubImagePlugin.py
venv/lib/python3.8/site-packages/PIL/Hdf5StubImagePlugin.py
venv/lib/python3.8/site-packages/PIL/IcnsImagePlugin.py
venv/lib/python3.8/site-packages/PIL/IcoImagePlugin.py
venv/lib/python3.8/site-packages/PIL/ImImagePlugin.py
venv/lib/python3.8/site-packages/PIL/Image.py
venv/lib/python3.8/site-packages/PIL/ImageChops.py
venv/lib/python3.8/site-packages/PIL/ImageCms.py
venv/lib/python3.8/site-packages/PIL/ImageColor.py
venv/lib/python3.8/site-packages/Pillow-8.2.0.dist-info/top_level.txt
venv/lib/python3.8/site-packages/pip-19.0.3-py3.8.egg/EGG-INFO/SOURCES.txt
venv/lib/python3.8/site-packages/pip-19.0.3-py3.8.egg/EGG-INFO/dependency_links.txt
venv/lib/python3.8/site-packages/pip-19.0.3-py3.8.egg/EGG-INFO/entry_points.txt
venv/lib/python3.8/site-packages/pip-19.0.3-py3.8.egg/EGG-INFO/top_level.txt
